birdcage/__init__.py
birdcage/v1_11/__init__.py
birdcage/v1_11/csrf.py
django_birdcage-1.0.0.dist-info/DESCRIPTION.rst
django_birdcage-1.0.0.dist-info/METADATA
django_birdcage-1.0.0.dist-info/RECORD
django_birdcage-1.0.0.dist-info/WHEEL
django_birdcage-1.0.0.dist-info/metadata.json
django_birdcage-1.0.0.dist-info/top_level.txt
tests/v1_11/__init__.py
tests/v1_11/test_csrf.py
