Metadata-Version: 2.0
Name: django-birdcage
Version: 1.0.0
Summary: Utilities for maintaining forwards compatibility with Django releases.
Home-page: http://github.com/zapier/django-birdcage
Author: Russell Keith-Magee
Author-email: russell.keith-magee@zapier.com
License: New BSD
Keywords: birdcage,Django,compatibility
Platform: UNKNOWN
Classifier: Development Status :: 5 - Production/Stable
Classifier: Intended Audience :: Developers
Classifier: License :: OSI Approved :: BSD License
Classifier: Operating System :: OS Independent
Classifier: Programming Language :: Python :: 2
Classifier: Programming Language :: Python :: 2.7
Classifier: Programming Language :: Python :: 3
Classifier: Programming Language :: Python :: 3.4
Classifier: Programming Language :: Python :: 3.5
Classifier: Programming Language :: Python :: 3.6
Classifier: Framework :: Django
Classifier: Framework :: Django :: 1.8
Classifier: Topic :: Software Development
Classifier: Topic :: Utilities
